package com.laioffer.ç¬¬2éƒ¨åˆ†_é«˜çº§.ç¬¬3ç« _é”.demo2_ä»å­—èŠ‚ç è§’åº¦åˆ†æsynchronized;

/**
 * ç±»çš„æè¿°: ä»å­—èŠ‚ç è§’åº¦åˆ†æã€ŒåŒæ­¥ä»£ç å—ã€
 * Created by æ˜¥å¤ç§‹å†¬åœ¨ä¸­å— on 2023/7/13 23:00
 */
public class Demo321 {
  Object o = new Object();

  public void foo() {
    synchronized (o) {
      System.out.println("åŒæ­¥ä»£ç å—");

      throw new RuntimeException("éªŒè¯æ˜¯å¦æ˜¯1ä¸ªmonitorenterå’Œ2ä¸ªmonitorexit");
    }
  }

  public static void main(String[] args) {
  }
}


/*
 ç”Ÿæˆçš„Classæ–‡ä»¶ åœ¨ "build/intermediates/javac/debug/classes/com/laioffer/ç¬¬2éƒ¨åˆ†_é«˜çº§/ç¬¬3ç« _é”/demo2_ä»å­—èŠ‚ç è§’åº¦åˆ†æsynchronized" ç›®å½•ä¸­

1. åç¼–è¯‘: javap -c Demo21.class

  public void foo();
    Code:
       0: aload_0
       1: getfield      #7                  // Field o:Ljava/lang/Object;
       4: dup
       5: astore_1
       6: monitorenter          ğŸ‘ˆğŸ» è·å¾—é”ğŸ”
       7: getstatic     #13                 // Field java/lang/System.out:Ljava/io/PrintStream;
      10: ldc           #19                 // String åŒæ­¥ä»£ç å—
      12: invokevirtual #21                 // Method java/io/PrintStream.println:(Ljava/lang/String;)V
      15: aload_1
      16: monitorexit           ğŸ‘ˆğŸ» é‡Šæ”¾é”ğŸ” â† ç¨‹åºè¿è¡Œæ­£å¸¸æƒ…å†µä¸‹ï¼Œæ­£å¸¸é€€å‡ºé”
      17: goto          25
      20: astore_2
      21: aload_1
      22: monitorexit           ğŸ‘ˆğŸ» æ­¤å¤„ä¸ºä»€ä¹ˆä¼šå¤šå‡ºä¸€ä¸ªmonitorexit â† ç¨‹åºå¼‚å¸¸æƒ…å†µä¸‹ï¼Œä¿è¯ä¹Ÿèƒ½é€€å‡ºé”çš„æŒæœ‰
      23: aload_2
      24: athrow
      25: return


2. å°ç»“
  ã€ŒåŒæ­¥ä»£ç å—ã€å®ç°åŸç†: ä½¿ç”¨çš„æ˜¯monitorenterå’ŒmonitorexitæŒ‡ä»¤

3. ä¸€å®šæ˜¯ä¸€ä¸ªenterå’Œä¸¤ä¸ªexitå—ï¼Ÿ
     i. ä¸€èˆ¬æ˜¯1ä¸ªmonitorenterå’Œ2ä¸ªmonitorexitæŒ‡ä»¤
     ii. ç‰¹æ®Šæƒ…å†µï¼Œå¦‚ throw new RuntimeException("xxxx");
        å†æ‰§è¡Œ javap -c Demo321.class

    public void foo();
      Code:
         0: aload_0
         1: getfield      #7                  // Field o:Ljava/lang/Object;
         4: dup
         5: astore_1
         6: monitorenter        ğŸ‘ˆğŸ» è·å¾—é”ğŸ”
         7: getstatic     #13                 // Field java/lang/System.out:Ljava/io/PrintStream;
        10: ldc           #19                 // String åŒæ­¥ä»£ç å—
        12: invokevirtual #21                 // Method java/io/PrintStream.println:(Ljava/lang/String;)V
        15: new           #27                 // class java/lang/RuntimeException
        18: dup
        19: ldc           #29                 // String éªŒè¯æ˜¯å¦æ˜¯1ä¸ªmonitorenterå’Œ2ä¸ªmonitorexit
        21: invokespecial #31                 // Method java/lang/RuntimeException."<init>":(Ljava/lang/String;)V
        24: athrow
        25: astore_2
        26: aload_1
        27: monitorexit         ğŸ‘ˆğŸ» å¼‚å¸¸é€€å‡ºï¼Œé‡Šæ”¾é”ğŸ”
        28: aload_2
        29: athrow



*/
